{
  "fetched_at": "2026-05-01 14:52",
  "episodes": [
    {
      "season": "1",
      "episode": "1",
      "guest": "Jennifer Lee",
      "class_year": "2003",
      "host": "GG",
      "recording": "Done",
      "teaser_upload": "Complete",
      "teaser_release": "4/24/25",
      "episode_upload": "Complete",
      "episode_release": "5/1/25",
      "2m_release": "Done"
    },
    {
      "season": "1",
      "episode": "2",
      "guest": "Brian Lin",
      "class_year": "2003",
      "host": "GG",
      "recording": "Done",
      "teaser_upload": "Complete",
      "teaser_release": "5/1/25",
      "episode_upload": "Complete",
      "episode_release": "5/8/25",
      "2m_release": "Done"
    },
    {
      "season": "1",
      "episode": "3",
      "guest": "Karen Ling",
      "class_year": "2003",
      "host": "GG",
      "recording": "Done",
      "teaser_upload": "Complete",
      "teaser_release": "5/8/25",
      "episode_upload": "Complete",
      "episode_release": "5/15/25",
      "2m_release": "Done"
    },
    {
      "season": "1",
      "episode": "4",
      "guest": "Carol Chan",
      "class_year": "2003",
      "host": "GG",
      "recording": "Done",
      "teaser_upload": "Complete",
      "teaser_release": "5/15/25",
      "episode_upload": "Complete",
      "episode_release": "5/22/25",
      "2m_release": "Done"
    },
    {
      "season": "1",
      "episode": "5",
      "guest": "Pierre Lam",
      "class_year": "2003",
      "host": "GG",
      "recording": "Done",
      "teaser_upload": "Complete",
      "teaser_release": "5/22/25",
      "episode_upload": "Complete",
      "episode_release": "5/29/25",
      "2m_release": "Done"
    },
    {
      "season": "1",
      "episode": "6",
      "guest": "Wynne Tong",
      "class_year": "2003",
      "host": "GG",
      "recording": "Done",
      "teaser_upload": "Complete",
      "teaser_release": "5/29/25",
      "episode_upload": "Complete",
      "episode_release": "6/5/25",
      "2m_release": "Done"
    },
    {
      "season": "1",
      "episode": "7",
      "guest": "Gerald Yeung",
      "class_year": "2003",
      "host": "GG",
      "recording": "Done",
      "teaser_upload": "Complete",
      "teaser_release": "6/5/25",
      "episode_upload": "Complete",
      "episode_release": "6/12/25",
      "2m_release": "Done"
    },
    {
      "season": "1",
      "episode": "8",
      "guest": "Gladys Tse",
      "class_year": "2003",
      "host": "GG",
      "recording": "Done",
      "teaser_upload": "Complete",
      "teaser_release": "6/12/25",
      "episode_upload": "Complete",
      "episode_release": "6/19/25",
      "2m_release": "Done"
    },
    {
      "season": "1",
      "episode": "9",
      "guest": "Vivian Wu",
      "class_year": "2003",
      "host": "GG",
      "recording": "Done",
      "teaser_upload": "Complete",
      "teaser_release": "6/19/25",
      "episode_upload": "Complete",
      "episode_release": "6/26/25",
      "2m_release": "Done"
    },
    {
      "season": "",
      "episode": "",
      "guest": "",
      "class_year": "",
      "host": "",
      "recording": "",
      "teaser_upload": "",
      "teaser_release": "",
      "episode_upload": "",
      "episode_release": "",
      "2m_release": ""
    },
    {
      "season": "2",
      "episode": "1",
      "guest": "Robert Sit",
      "class_year": "2003",
      "host": "GG",
      "recording": "Done",
      "teaser_upload": "Complete",
      "teaser_release": "7/3/2025",
      "episode_upload": "Complete",
      "episode_release": "7/10/2025",
      "2m_release": "Done"
    },
    {
      "season": "2",
      "episode": "2",
      "guest": "Helen Wong",
      "class_year": "2003",
      "host": "GG",
      "recording": "Done",
      "teaser_upload": "Complete",
      "teaser_release": "7/10/2025",
      "episode_upload": "Complete",
      "episode_release": "7/17/2025",
      "2m_release": "Done"
    },
    {
      "season": "2",
      "episode": "3",
      "guest": "Stephen Ng",
      "class_year": "2003",
      "host": "GG",
      "recording": "Done",
      "teaser_upload": "Complete",
      "teaser_release": "7/17/2025",
      "episode_upload": "Complete",
      "episode_release": "7/24/2025",
      "2m_release": "Done"
    },
    {
      "season": "2",
      "episode": "4",
      "guest": "Natalie Ko",
      "class_year": "2003",
      "host": "GG",
      "recording": "Done",
      "teaser_upload": "Complete",
      "teaser_release": "7/24/2025",
      "episode_upload": "Complete",
      "episode_release": "7/31/2025",
      "2m_release": "Done"
    },
    {
      "season": "2",
      "episode": "5",
      "guest": "Ivan Leung",
      "class_year": "2003",
      "host": "GG",
      "recording": "Done",
      "teaser_upload": "Complete",
      "teaser_release": "7/31/2025",
      "episode_upload": "Complete",
      "episode_release": "8/7/2025",
      "2m_release": "Done"
    },
    {
      "season": "2",
      "episode": "6",
      "guest": "Fong Tze Kit",
      "class_year": "2003",
      "host": "GG",
      "recording": "Done",
      "teaser_upload": "Complete",
      "teaser_release": "8/7/2025",
      "episode_upload": "Complete",
      "episode_release": "8/14/2025",
      "2m_release": "Done"
    },
    {
      "season": "2",
      "episode": "7",
      "guest": "Grace Lo",
      "class_year": "2003",
      "host": "GG",
      "recording": "Done",
      "teaser_upload": "Complete",
      "teaser_release": "8/14/2025",
      "episode_upload": "Complete",
      "episode_release": "8/21/2025",
      "2m_release": "Done"
    },
    {
      "season": "2",
      "episode": "8",
      "guest": "Jonathan So",
      "class_year": "2003",
      "host": "GG",
      "recording": "Done",
      "teaser_upload": "Complete",
      "teaser_release": "8/21/2025",
      "episode_upload": "Complete",
      "episode_release": "8/28/2025",
      "2m_release": "Done"
    },
    {
      "season": "2",
      "episode": "9",
      "guest": "Deanna Law",
      "class_year": "2003",
      "host": "GG",
      "recording": "Done",
      "teaser_upload": "Complete",
      "teaser_release": "8/28/2025",
      "episode_upload": "Complete",
      "episode_release": "9/4/2025",
      "2m_release": "Done"
    },
    {
      "season": "",
      "episode": "",
      "guest": "",
      "class_year": "",
      "host": "",
      "recording": "",
      "teaser_upload": "",
      "teaser_release": "",
      "episode_upload": "",
      "episode_release": "",
      "2m_release": ""
    },
    {
      "season": "3",
      "episode": "1",
      "guest": "Mark Law",
      "class_year": "2003",
      "host": "GG",
      "recording": "Done",
      "teaser_upload": "Complete",
      "teaser_release": "9/11/2025",
      "episode_upload": "Complete",
      "episode_release": "9/18/2025",
      "2m_release": "Done"
    },
    {
      "season": "3",
      "episode": "2",
      "guest": "Dionne Hui",
      "class_year": "2003",
      "host": "GG",
      "recording": "Done",
      "teaser_upload": "Complete",
      "teaser_release": "9/18/2025",
      "episode_upload": "Complete",
      "episode_release": "9/25/2025",
      "2m_release": "Done"
    },
    {
      "season": "3",
      "episode": "3",
      "guest": "Clement Cheng",
      "class_year": "2005",
      "host": "GG",
      "recording": "Done",
      "teaser_upload": "Complete",
      "teaser_release": "9/25/2025",
      "episode_upload": "Complete",
      "episode_release": "10/2/2025",
      "2m_release": "Done"
    },
    {
      "season": "3",
      "episode": "4",
      "guest": "Ringo Ho",
      "class_year": "2003",
      "host": "GG",
      "recording": "Done",
      "teaser_upload": "Complete",
      "teaser_release": "10/2/2025",
      "episode_upload": "Complete",
      "episode_release": "10/9/2025",
      "2m_release": "Done"
    },
    {
      "season": "3",
      "episode": "5",
      "guest": "Karen Chiu",
      "class_year": "2003",
      "host": "GG",
      "recording": "Done",
      "teaser_upload": "Complete",
      "teaser_release": "10/9/2025",
      "episode_upload": "Complete",
      "episode_release": "10/16/2025",
      "2m_release": "Done"
    },
    {
      "season": "3",
      "episode": "6",
      "guest": "Gary Ho",
      "class_year": "2003",
      "host": "GG",
      "recording": "Done",
      "teaser_upload": "Complete",
      "teaser_release": "10/16/2025",
      "episode_upload": "Complete",
      "episode_release": "10/23/2025",
      "2m_release": "Done"
    },
    {
      "season": "3",
      "episode": "7",
      "guest": "Cassie Mak",
      "class_year": "2001",
      "host": "GG",
      "recording": "Done",
      "teaser_upload": "Complete",
      "teaser_release": "10/23/2025",
      "episode_upload": "Complete",
      "episode_release": "10/30/2025",
      "2m_release": "Done"
    },
    {
      "season": "3",
      "episode": "8",
      "guest": "Andre Lin",
      "class_year": "2003",
      "host": "GG",
      "recording": "Done",
      "teaser_upload": "Complete",
      "teaser_release": "10/30/2025",
      "episode_upload": "Complete",
      "episode_release": "11/6/2025",
      "2m_release": "Done"
    },
    {
      "season": "3",
      "episode": "9",
      "guest": "Jackie Au",
      "class_year": "2002",
      "host": "GG",
      "recording": "Done",
      "teaser_upload": "Complete",
      "teaser_release": "11/6/2025",
      "episode_upload": "Complete",
      "episode_release": "11/13/2025",
      "2m_release": "Done"
    },
    {
      "season": "",
      "episode": "",
      "guest": "",
      "class_year": "",
      "host": "",
      "recording": "",
      "teaser_upload": "",
      "teaser_release": "",
      "episode_upload": "",
      "episode_release": "",
      "2m_release": ""
    },
    {
      "season": "4",
      "episode": "1",
      "guest": "Russell Fok",
      "class_year": "2003",
      "host": "GG",
      "recording": "Done",
      "teaser_upload": "Complete",
      "teaser_release": "11/20/2025",
      "episode_upload": "Complete",
      "episode_release": "12/5/2025",
      "2m_release": "Done"
    },
    {
      "season": "4",
      "episode": "2",
      "guest": "Janice Wong",
      "class_year": "2005",
      "host": "GG",
      "recording": "Done",
      "teaser_upload": "Complete",
      "teaser_release": "12/4/2025",
      "episode_upload": "Complete",
      "episode_release": "12/11/2025",
      "2m_release": "Done"
    },
    {
      "season": "4",
      "episode": "3",
      "guest": "Adrian Tso",
      "class_year": "2003",
      "host": "GG",
      "recording": "Done",
      "teaser_upload": "Complete",
      "teaser_release": "12/11/2025",
      "episode_upload": "Complete",
      "episode_release": "12/18/2025",
      "2m_release": "Done"
    },
    {
      "season": "4",
      "episode": "4",
      "guest": "Holiday Get Together",
      "class_year": "-",
      "host": "Community",
      "recording": "-",
      "teaser_upload": "-",
      "teaser_release": "-",
      "episode_upload": "Complete",
      "episode_release": "12/14/2025",
      "2m_release": "N/A"
    },
    {
      "season": "4",
      "episode": "5",
      "guest": "Year End Episode",
      "class_year": "-",
      "host": "FTK & GG",
      "recording": "Dec 12",
      "teaser_upload": "Complete",
      "teaser_release": "12/18/2025",
      "episode_upload": "Complete",
      "episode_release": "12/25/2025",
      "2m_release": "N/A"
    },
    {
      "season": "",
      "episode": "",
      "guest": "",
      "class_year": "",
      "host": "",
      "recording": "",
      "teaser_upload": "",
      "teaser_release": "",
      "episode_upload": "",
      "episode_release": "",
      "2m_release": ""
    },
    {
      "season": "5",
      "episode": "1",
      "guest": "Jerry Hung",
      "class_year": "2003",
      "host": "GG",
      "recording": "Done",
      "teaser_upload": "",
      "teaser_release": "1/1/2026",
      "episode_upload": "",
      "episode_release": "1/8/2026",
      "2m_release": "Done"
    },
    {
      "season": "5",
      "episode": "2",
      "guest": "Jimmy Chan",
      "class_year": "2003",
      "host": "GG",
      "recording": "Done",
      "teaser_upload": "",
      "teaser_release": "1/8/2026",
      "episode_upload": "",
      "episode_release": "1/15/2026",
      "2m_release": "Done"
    },
    {
      "season": "5",
      "episode": "3",
      "guest": "Sunny Pau",
      "class_year": "2003",
      "host": "GG",
      "recording": "Done",
      "teaser_upload": "",
      "teaser_release": "1/15/2026",
      "episode_upload": "",
      "episode_release": "1/22/2026",
      "2m_release": "Done"
    },
    {
      "season": "5",
      "episode": "4",
      "guest": "Jac Lee",
      "class_year": "2003",
      "host": "GG",
      "recording": "Done",
      "teaser_upload": "",
      "teaser_release": "1/22/2026",
      "episode_upload": "",
      "episode_release": "1/29/2026",
      "2m_release": ""
    },
    {
      "season": "5",
      "episode": "5",
      "guest": "Jeffrey Chan",
      "class_year": "2003",
      "host": "GG",
      "recording": "Done",
      "teaser_upload": "",
      "teaser_release": "1/29/2026",
      "episode_upload": "",
      "episode_release": "2/5/2026",
      "2m_release": ""
    },
    {
      "season": "5",
      "episode": "6",
      "guest": "Lok Lam",
      "class_year": "2003",
      "host": "FTK",
      "recording": "Done",
      "teaser_upload": "",
      "teaser_release": "2/5/2026",
      "episode_upload": "",
      "episode_release": "2/12/2026",
      "2m_release": ""
    },
    {
      "season": "-",
      "episode": "-",
      "guest": "CNY HOLIDAY",
      "class_year": "-",
      "host": "",
      "recording": "-",
      "teaser_upload": "",
      "teaser_release": "-",
      "episode_upload": "",
      "episode_release": "2/19/2026",
      "2m_release": ""
    },
    {
      "season": "5",
      "episode": "7",
      "guest": "Steph + Jody Part 1",
      "class_year": "2003",
      "host": "GG",
      "recording": "Done",
      "teaser_upload": "",
      "teaser_release": "2/12/2026",
      "episode_upload": "",
      "episode_release": "2/25/2026",
      "2m_release": ""
    },
    {
      "season": "5",
      "episode": "8",
      "guest": "Steph + Jody Part 2",
      "class_year": "2003",
      "host": "GG",
      "recording": "Done",
      "teaser_upload": "",
      "teaser_release": "N/A",
      "episode_upload": "",
      "episode_release": "2/26/2026",
      "2m_release": ""
    },
    {
      "season": "5",
      "episode": "9",
      "guest": "Mr Yuen Part 1",
      "class_year": "Staff",
      "host": "GG",
      "recording": "Done",
      "teaser_upload": "",
      "teaser_release": "2/26/2026",
      "episode_upload": "",
      "episode_release": "3/5/2026",
      "2m_release": ""
    },
    {
      "season": "5",
      "episode": "10",
      "guest": "Mr Yuen Part 2",
      "class_year": "Staff",
      "host": "GG",
      "recording": "Done",
      "teaser_upload": "",
      "teaser_release": "3/5/2026",
      "episode_upload": "",
      "episode_release": "3/12/2026",
      "2m_release": ""
    },
    {
      "season": "5",
      "episode": "11",
      "guest": "S5 Summary",
      "class_year": "-",
      "host": "FTK & GG",
      "recording": "Done",
      "teaser_upload": "",
      "teaser_release": "3/12/2026",
      "episode_upload": "",
      "episode_release": "3/19/2026",
      "2m_release": ""
    },
    {
      "season": "",
      "episode": "",
      "guest": "",
      "class_year": "",
      "host": "",
      "recording": "",
      "teaser_upload": "",
      "teaser_release": "",
      "episode_upload": "",
      "episode_release": "",
      "2m_release": ""
    },
    {
      "season": "6",
      "episode": "1",
      "guest": "Lung Sir",
      "class_year": "1999",
      "host": "Jerry",
      "recording": "Done",
      "teaser_upload": "",
      "teaser_release": "3/19/2026",
      "episode_upload": "",
      "episode_release": "3/26/2026",
      "2m_release": ""
    },
    {
      "season": "Nonsense",
      "episode": "N/A",
      "guest": "April Fools 2026",
      "class_year": "-",
      "host": "DJ & GG",
      "recording": "Done",
      "teaser_upload": "",
      "teaser_release": "",
      "episode_upload": "",
      "episode_release": "4/1/2026",
      "2m_release": ""
    },
    {
      "season": "Nonsense",
      "episode": "N/A",
      "guest": "Soccer Video",
      "class_year": "-",
      "host": "-",
      "recording": "Done",
      "teaser_upload": "",
      "teaser_release": "",
      "episode_upload": "",
      "episode_release": "4/2/2016",
      "2m_release": ""
    },
    {
      "season": "6",
      "episode": "2",
      "guest": "Jeff Kwok",
      "class_year": "2003",
      "host": "GG",
      "recording": "Done",
      "teaser_upload": "",
      "teaser_release": "3/26 and 4/3",
      "episode_upload": "",
      "episode_release": "4/9/2026",
      "2m_release": ""
    },
    {
      "season": "6",
      "episode": "3",
      "guest": "Ms Leung Lai Mei",
      "class_year": "Staff",
      "host": "GG",
      "recording": "Done",
      "teaser_upload": "",
      "teaser_release": "4/9/2026",
      "episode_upload": "",
      "episode_release": "4/16/2026",
      "2m_release": ""
    },
    {
      "season": "6",
      "episode": "4",
      "guest": "SPCCAC Denise Yam",
      "class_year": "1991",
      "host": "Sunny",
      "recording": "Done",
      "teaser_upload": "",
      "teaser_release": "4/16/2026",
      "episode_upload": "",
      "episode_release": "4/23/2026",
      "2m_release": ""
    },
    {
      "season": "6",
      "episode": "5",
      "guest": "Michael Wong",
      "class_year": "2003",
      "host": "GG",
      "recording": "Done",
      "teaser_upload": "",
      "teaser_release": "4/23/2026",
      "episode_upload": "",
      "episode_release": "4/30/2026",
      "2m_release": ""
    },
    {
      "season": "6",
      "episode": "6",
      "guest": "Clement Yeung",
      "class_year": "2005",
      "host": "Janice",
      "recording": "Done",
      "teaser_upload": "",
      "teaser_release": "4/30/2026",
      "episode_upload": "",
      "episode_release": "5/7/2026",
      "2m_release": ""
    },
    {
      "season": "6",
      "episode": "7",
      "guest": "Eric Cheung",
      "class_year": "2003",
      "host": "GG",
      "recording": "Done",
      "teaser_upload": "",
      "teaser_release": "5/7/2026",
      "episode_upload": "",
      "episode_release": "5/14/2026",
      "2m_release": ""
    },
    {
      "season": "6",
      "episode": "8",
      "guest": "Kristen Chin",
      "class_year": "2002",
      "host": "Jackie",
      "recording": "Done",
      "teaser_upload": "",
      "teaser_release": "5/14/2026",
      "episode_upload": "",
      "episode_release": "5/21/2026",
      "2m_release": ""
    },
    {
      "season": "Nonsense",
      "episode": "N/A",
      "guest": "Tang East",
      "class_year": "-",
      "host": "Community",
      "recording": "Done",
      "teaser_upload": "",
      "teaser_release": "5/21/2026",
      "episode_upload": "",
      "episode_release": "5/28/2026",
      "2m_release": ""
    },
    {
      "season": "6",
      "episode": "9",
      "guest": "1 year Anniversary",
      "class_year": "-",
      "host": "",
      "recording": "",
      "teaser_upload": "",
      "teaser_release": "5/28/2026",
      "episode_upload": "",
      "episode_release": "6/4/2026",
      "2m_release": ""
    },
    {
      "season": "Nonsense",
      "episode": "N/A",
      "guest": "Ryan Kam Soccer",
      "class_year": "-",
      "host": "",
      "recording": "",
      "teaser_upload": "",
      "teaser_release": "5/28/2026",
      "episode_upload": "",
      "episode_release": "6/9/2026",
      "2m_release": ""
    },
    {
      "season": "Nonsense",
      "episode": "N/A",
      "guest": "2024 Soccer",
      "class_year": "-",
      "host": "",
      "recording": "",
      "teaser_upload": "",
      "teaser_release": "5/28/2026",
      "episode_upload": "",
      "episode_release": "6/10/2026",
      "2m_release": ""
    },
    {
      "season": "7",
      "episode": "1",
      "guest": "Jeff Shum",
      "class_year": "2003",
      "host": "GG",
      "recording": "Done",
      "teaser_upload": "",
      "teaser_release": "6/4/2026",
      "episode_upload": "",
      "episode_release": "6/18/2026",
      "2m_release": ""
    },
    {
      "season": "7",
      "episode": "2",
      "guest": "Ms Wong MK",
      "class_year": "Staff",
      "host": "GG",
      "recording": "Done",
      "teaser_upload": "",
      "teaser_release": "6/11/2026",
      "episode_upload": "",
      "episode_release": "6/25/2026",
      "2m_release": ""
    },
    {
      "season": "7",
      "episode": "3",
      "guest": "Kevin Law",
      "class_year": "2004",
      "host": "GG",
      "recording": "TBD",
      "teaser_upload": "",
      "teaser_release": "6/18/2026",
      "episode_upload": "",
      "episode_release": "7/2/2026",
      "2m_release": ""
    },
    {
      "season": "7",
      "episode": "4",
      "guest": "Anthony Choi",
      "class_year": "2003",
      "host": "FTK",
      "recording": "Done",
      "teaser_upload": "",
      "teaser_release": "6/25/2026",
      "episode_upload": "",
      "episode_release": "7/9/2026",
      "2m_release": ""
    },
    {
      "season": "7",
      "episode": "5",
      "guest": "James Lam",
      "class_year": "2004",
      "host": "Sunny",
      "recording": "Done",
      "teaser_upload": "",
      "teaser_release": "7/2/2026",
      "episode_upload": "",
      "episode_release": "7/16/2026",
      "2m_release": ""
    },
    {
      "season": "7",
      "episode": "6",
      "guest": "Arthur Mui",
      "class_year": "2003",
      "host": "David",
      "recording": "",
      "teaser_upload": "",
      "teaser_release": "7/9/2026",
      "episode_upload": "",
      "episode_release": "7/23/2026",
      "2m_release": ""
    },
    {
      "season": "7",
      "episode": "7",
      "guest": "Paulino Ho",
      "class_year": "2003",
      "host": "TBD",
      "recording": "",
      "teaser_upload": "",
      "teaser_release": "7/16/2026",
      "episode_upload": "",
      "episode_release": "7/30/2026",
      "2m_release": ""
    },
    {
      "season": "7",
      "episode": "8",
      "guest": "Geoffrey Ko",
      "class_year": "1969",
      "host": "Sunny",
      "recording": "May 22",
      "teaser_upload": "",
      "teaser_release": "7/23/2026",
      "episode_upload": "",
      "episode_release": "7/30/2026",
      "2m_release": ""
    },
    {
      "season": "7",
      "episode": "9",
      "guest": "David Chen",
      "class_year": "2003",
      "host": "",
      "recording": "",
      "teaser_upload": "",
      "teaser_release": "7/30/2026",
      "episode_upload": "",
      "episode_release": "8/6/2026",
      "2m_release": ""
    },
    {
      "season": "7",
      "episode": "10",
      "guest": "S7 Summary",
      "class_year": "-",
      "host": "",
      "recording": "",
      "teaser_upload": "",
      "teaser_release": "8/6/2026",
      "episode_upload": "",
      "episode_release": "8/13/2026",
      "2m_release": ""
    },
    {
      "season": "",
      "episode": "",
      "guest": "",
      "class_year": "",
      "host": "",
      "recording": "",
      "teaser_upload": "",
      "teaser_release": "",
      "episode_upload": "",
      "episode_release": "",
      "2m_release": ""
    },
    {
      "season": "TBD",
      "episode": "",
      "guest": "Ma Sir ",
      "class_year": "",
      "host": "",
      "recording": "Done",
      "teaser_upload": "",
      "teaser_release": "",
      "episode_upload": "",
      "episode_release": "",
      "2m_release": ""
    },
    {
      "season": "Agreed",
      "episode": "",
      "guest": "Karita Kan",
      "class_year": "",
      "host": "",
      "recording": "",
      "teaser_upload": "",
      "teaser_release": "",
      "episode_upload": "",
      "episode_release": "",
      "2m_release": ""
    },
    {
      "season": "Agreed",
      "episode": "",
      "guest": "McDull",
      "class_year": "",
      "host": "",
      "recording": "Losing Weight",
      "teaser_upload": "",
      "teaser_release": "",
      "episode_upload": "",
      "episode_release": "",
      "2m_release": ""
    },
    {
      "season": "Agreed",
      "episode": "",
      "guest": "Francis Tso",
      "class_year": "",
      "host": "",
      "recording": "",
      "teaser_upload": "",
      "teaser_release": "",
      "episode_upload": "",
      "episode_release": "",
      "2m_release": ""
    },
    {
      "season": "Agreed",
      "episode": "",
      "guest": "Cora Ling",
      "class_year": "",
      "host": "",
      "recording": "",
      "teaser_upload": "",
      "teaser_release": "",
      "episode_upload": "",
      "episode_release": "",
      "2m_release": ""
    },
    {
      "season": "Agreed",
      "episode": "",
      "guest": "Lok Man Lee",
      "class_year": "",
      "host": "",
      "recording": "",
      "teaser_upload": "",
      "teaser_release": "",
      "episode_upload": "",
      "episode_release": "",
      "2m_release": ""
    },
    {
      "season": "Agreed",
      "episode": "",
      "guest": "Nick Bong Lee",
      "class_year": "",
      "host": "",
      "recording": "",
      "teaser_upload": "",
      "teaser_release": "",
      "episode_upload": "",
      "episode_release": "",
      "2m_release": ""
    },
    {
      "season": "Agreed",
      "episode": "",
      "guest": "Clement Pang",
      "class_year": "",
      "host": "",
      "recording": "",
      "teaser_upload": "",
      "teaser_release": "",
      "episode_upload": "",
      "episode_release": "",
      "2m_release": ""
    },
    {
      "season": "Agreed",
      "episode": "",
      "guest": "Zoie Teng",
      "class_year": "",
      "host": "",
      "recording": "Check in later",
      "teaser_upload": "",
      "teaser_release": "",
      "episode_upload": "",
      "episode_release": "",
      "2m_release": ""
    },
    {
      "season": "Agreed",
      "episode": "",
      "guest": "Cherky",
      "class_year": "",
      "host": "",
      "recording": "",
      "teaser_upload": "",
      "teaser_release": "",
      "episode_upload": "",
      "episode_release": "",
      "2m_release": ""
    },
    {
      "season": "Agreed",
      "episode": "",
      "guest": "Michael Tsang",
      "class_year": "",
      "host": "",
      "recording": "",
      "teaser_upload": "",
      "teaser_release": "",
      "episode_upload": "",
      "episode_release": "",
      "2m_release": ""
    },
    {
      "season": "Agreed",
      "episode": "",
      "guest": "Tak Yee Yung",
      "class_year": "",
      "host": "",
      "recording": "",
      "teaser_upload": "",
      "teaser_release": "",
      "episode_upload": "",
      "episode_release": "",
      "2m_release": ""
    },
    {
      "season": "Agreed",
      "episode": "",
      "guest": "Chris Wong",
      "class_year": "",
      "host": "",
      "recording": "",
      "teaser_upload": "",
      "teaser_release": "",
      "episode_upload": "",
      "episode_release": "",
      "2m_release": ""
    },
    {
      "season": "Agreed",
      "episode": "",
      "guest": "Jason Kung",
      "class_year": "",
      "host": "",
      "recording": "",
      "teaser_upload": "",
      "teaser_release": "",
      "episode_upload": "",
      "episode_release": "",
      "2m_release": ""
    },
    {
      "season": "Agreed",
      "episode": "",
      "guest": "Wilson Lok",
      "class_year": "",
      "host": "",
      "recording": "",
      "teaser_upload": "",
      "teaser_release": "",
      "episode_upload": "",
      "episode_release": "",
      "2m_release": ""
    },
    {
      "season": "Agreed",
      "episode": "",
      "guest": "",
      "class_year": "",
      "host": "",
      "recording": "",
      "teaser_upload": "",
      "teaser_release": "",
      "episode_upload": "",
      "episode_release": "",
      "2m_release": ""
    },
    {
      "season": "Agreed",
      "episode": "",
      "guest": "",
      "class_year": "",
      "host": "",
      "recording": "",
      "teaser_upload": "",
      "teaser_release": "",
      "episode_upload": "",
      "episode_release": "",
      "2m_release": ""
    },
    {
      "season": "Agreed",
      "episode": "",
      "guest": "",
      "class_year": "",
      "host": "",
      "recording": "",
      "teaser_upload": "",
      "teaser_release": "",
      "episode_upload": "",
      "episode_release": "",
      "2m_release": ""
    },
    {
      "season": "",
      "episode": "",
      "guest": "",
      "class_year": "",
      "host": "",
      "recording": "",
      "teaser_upload": "",
      "teaser_release": "",
      "episode_upload": "",
      "episode_release": "",
      "2m_release": ""
    },
    {
      "season": "",
      "episode": "",
      "guest": "",
      "class_year": "",
      "host": "",
      "recording": "",
      "teaser_upload": "",
      "teaser_release": "",
      "episode_upload": "",
      "episode_release": "",
      "2m_release": ""
    },
    {
      "season": "",
      "episode": "",
      "guest": "",
      "class_year": "",
      "host": "",
      "recording": "",
      "teaser_upload": "",
      "teaser_release": "",
      "episode_upload": "",
      "episode_release": "",
      "2m_release": ""
    },
    {
      "season": "",
      "episode": "",
      "guest": "",
      "class_year": "",
      "host": "",
      "recording": "",
      "teaser_upload": "",
      "teaser_release": "",
      "episode_upload": "",
      "episode_release": "",
      "2m_release": ""
    },
    {
      "season": "",
      "episode": "",
      "guest": "",
      "class_year": "",
      "host": "",
      "recording": "",
      "teaser_upload": "",
      "teaser_release": "",
      "episode_upload": "",
      "episode_release": "",
      "2m_release": ""
    },
    {
      "season": "Check back",
      "episode": "",
      "guest": "Kenneth King",
      "class_year": "",
      "host": "",
      "recording": "",
      "teaser_upload": "",
      "teaser_release": "",
      "episode_upload": "",
      "episode_release": "",
      "2m_release": ""
    },
    {
      "season": "Check back",
      "episode": "",
      "guest": "Jon Tam",
      "class_year": "",
      "host": "",
      "recording": "",
      "teaser_upload": "",
      "teaser_release": "",
      "episode_upload": "",
      "episode_release": "",
      "2m_release": ""
    },
    {
      "season": "Check back",
      "episode": "",
      "guest": "Lulu",
      "class_year": "",
      "host": "",
      "recording": "",
      "teaser_upload": "",
      "teaser_release": "",
      "episode_upload": "",
      "episode_release": "",
      "2m_release": ""
    },
    {
      "season": "Check back",
      "episode": "",
      "guest": "James (Galen) Yip",
      "class_year": "",
      "host": "",
      "recording": "",
      "teaser_upload": "",
      "teaser_release": "",
      "episode_upload": "",
      "episode_release": "",
      "2m_release": ""
    },
    {
      "season": "Check back",
      "episode": "",
      "guest": "Lo Duc Him",
      "class_year": "",
      "host": "",
      "recording": "",
      "teaser_upload": "",
      "teaser_release": "",
      "episode_upload": "",
      "episode_release": "",
      "2m_release": ""
    },
    {
      "season": "Check back",
      "episode": "",
      "guest": "Beatrice Lau",
      "class_year": "",
      "host": "",
      "recording": "",
      "teaser_upload": "",
      "teaser_release": "",
      "episode_upload": "",
      "episode_release": "",
      "2m_release": ""
    },
    {
      "season": "Check back",
      "episode": "",
      "guest": "Tiff Leung",
      "class_year": "",
      "host": "",
      "recording": "Check in in Nov",
      "teaser_upload": "",
      "teaser_release": "",
      "episode_upload": "",
      "episode_release": "",
      "2m_release": ""
    },
    {
      "season": "Check back",
      "episode": "",
      "guest": "Rachel Ma",
      "class_year": "",
      "host": "",
      "recording": "",
      "teaser_upload": "",
      "teaser_release": "",
      "episode_upload": "",
      "episode_release": "",
      "2m_release": ""
    },
    {
      "season": "Check back",
      "episode": "",
      "guest": "Finsen Chiu",
      "class_year": "",
      "host": "",
      "recording": "",
      "teaser_upload": "",
      "teaser_release": "",
      "episode_upload": "",
      "episode_release": "",
      "2m_release": ""
    },
    {
      "season": "Check back",
      "episode": "",
      "guest": "Kelvin Lau",
      "class_year": "",
      "host": "",
      "recording": "",
      "teaser_upload": "",
      "teaser_release": "",
      "episode_upload": "",
      "episode_release": "",
      "2m_release": ""
    },
    {
      "season": "Check back",
      "episode": "",
      "guest": "Ms Leung",
      "class_year": "",
      "host": "",
      "recording": "",
      "teaser_upload": "",
      "teaser_release": "",
      "episode_upload": "",
      "episode_release": "",
      "2m_release": ""
    },
    {
      "season": "Check back",
      "episode": "",
      "guest": "Ms Yiu",
      "class_year": "",
      "host": "",
      "recording": "",
      "teaser_upload": "",
      "teaser_release": "",
      "episode_upload": "",
      "episode_release": "",
      "2m_release": ""
    },
    {
      "season": "",
      "episode": "",
      "guest": "",
      "class_year": "",
      "host": "",
      "recording": "",
      "teaser_upload": "",
      "teaser_release": "",
      "episode_upload": "",
      "episode_release": "",
      "2m_release": ""
    },
    {
      "season": "",
      "episode": "",
      "guest": "",
      "class_year": "",
      "host": "",
      "recording": "",
      "teaser_upload": "",
      "teaser_release": "",
      "episode_upload": "",
      "episode_release": "",
      "2m_release": ""
    },
    {
      "season": "",
      "episode": "",
      "guest": "",
      "class_year": "",
      "host": "",
      "recording": "",
      "teaser_upload": "",
      "teaser_release": "",
      "episode_upload": "",
      "episode_release": "",
      "2m_release": ""
    },
    {
      "season": "",
      "episode": "",
      "guest": "",
      "class_year": "",
      "host": "",
      "recording": "",
      "teaser_upload": "",
      "teaser_release": "",
      "episode_upload": "",
      "episode_release": "",
      "2m_release": ""
    },
    {
      "season": "",
      "episode": "",
      "guest": "",
      "class_year": "",
      "host": "",
      "recording": "",
      "teaser_upload": "",
      "teaser_release": "",
      "episode_upload": "",
      "episode_release": "",
      "2m_release": ""
    },
    {
      "season": "",
      "episode": "",
      "guest": "",
      "class_year": "",
      "host": "",
      "recording": "",
      "teaser_upload": "",
      "teaser_release": "",
      "episode_upload": "",
      "episode_release": "",
      "2m_release": ""
    },
    {
      "season": "0",
      "episode": "",
      "guest": "",
      "class_year": "",
      "host": "",
      "recording": "",
      "teaser_upload": "",
      "teaser_release": "",
      "episode_upload": "",
      "episode_release": "",
      "2m_release": ""
    }
  ]
}